genai_core/__init__.py
genai_core/genai_core/__init__.py
genai_core/genai_core/cores/__init__.py
genai_core/genai_core/cores/embedding_models/__init__.py
genai_core/genai_core/cores/embedding_models/base_model.py
genai_core/genai_core/cores/embedding_models/bedrock_embeddings.py
genai_core/genai_core/cores/LLMs/__init__.py
genai_core/genai_core/cores/LLMs/bedrockLLM.py
genai_core/genai_core/cores/LLMs/LLM_base.py
genai_core/genai_core/cores/LLMs/mockLLM.py
genai_core/genai_core/cores/LLMs/OpenAILLM.py
genai_core/genai_core/functions/__init__.py
genai_core/genai_core/functions/FAQ/__init__.py
genai_core/genai_core/functions/FAQ/base_FAQ.py
genai_core/genai_core/functions/FAQ/opensearch_FAQ.py
genai_core/genai_core/functions/intent_classification/__init__.py
genai_core/genai_core/functions/intent_classification/base_classificator.py
genai_core/genai_core/functions/intent_classification/lgbm_intent_classificator.py
genai_core/genai_core/functions/intent_classification/mock_intent_classificator.py
genai_core/genai_core/functions/prompt_routing/__init__.py
genai_core/genai_core/functions/prompt_routing/base_prompt_routing.py
genai_core/genai_core/functions/prompt_routing/llm_prompt_routing.py
genai_core/genai_core/functions/question_rephrasing/__init__.py
genai_core/genai_core/functions/question_rephrasing/base_question_rephrasing.py
genai_core/genai_core/functions/question_rephrasing/llm_question_rephrasing.py
genai_core/genai_core/functions/retrievers/__init__.py
genai_core/genai_core/functions/retrievers/base_retriever.py
genai_core/genai_core/functions/retrievers/opensearch_retriever.py
genai_core/genai_core/logger/__init__.py
genai_core/genai_core/logger/logger.py
genai_core/genai_core/platform engines/__init__.py
genai_core/genai_core/utils/__init__.py
genai_core/genai_core/utils/state_machine/__init__.py
genai_core/genai_core/utils/state_machine/orchestrator.py
genai_core/genai_core/utils/state_machine/state.py
genai_core-0.1.0.dist-info/LICENSE
genai_core-0.1.0.dist-info/METADATA
genai_core-0.1.0.dist-info/WHEEL
genai_core-0.1.0.dist-info/RECORD
