Metadata-Version: 2.1
Name: genai-core
Version: 0.1.0
Summary: Common Generative-AI platform for Generali Group core functionalities
License: TODO
Author: Nicola Rosetti, Juri Fabbri
Requires-Python: >=3.9,<4.0
Classifier: License :: Other/Proprietary License
Classifier: Programming Language :: Python :: 3
Classifier: Programming Language :: Python :: 3.9
Classifier: Programming Language :: Python :: 3.10
Classifier: Programming Language :: Python :: 3.11
Requires-Dist: anthropic-bedrock (==0.8.0)
Requires-Dist: boto3 (==1.34.62)
Requires-Dist: botocore (==1.34.110)
Requires-Dist: joblib (==1.3.2)
Requires-Dist: langchain (==0.2.1)
Requires-Dist: langchain-community (==0.2.1)
Requires-Dist: langchain-core (==0.2.3)
Requires-Dist: lightgbm (==4.3.0)
Requires-Dist: numpy (==1.26.4)
Requires-Dist: opensearch-py (==2.4.2)
Requires-Dist: pytest (>=8.2.1,<9.0.0)
Requires-Dist: pyyaml (==6.0.1)
Requires-Dist: requests-aws4auth (==1.2.3)
Requires-Dist: transitions (==0.9.0)
